zipcreator/__init__.py
zipcreator/main.py
zipcreator_sebastian_stigler-0.1.1.dist-info/METADATA
zipcreator_sebastian_stigler-0.1.1.dist-info/WHEEL
zipcreator_sebastian_stigler-0.1.1.dist-info/entry_points.txt
zipcreator_sebastian_stigler-0.1.1.dist-info/licenses/LICENSE
zipcreator_sebastian_stigler-0.1.1.dist-info/RECORD
