Metadata-Version: 2.4
Name: zipcreator-sebastian-stigler
Version: 0.1.1
Summary: Creates a zip archive, excluding files matching .zipignore patterns, and adds a prefix inside the archive
Project-URL: Repository, https://in-stigler.htw-aalen.de/gitea/tools/zipcreator.git
Author-email: Sebastian Stigler <sebastian.stigler@hs-aalen.de>
License: MIT
License-File: LICENSE
Requires-Python: >=3.10
Requires-Dist: pathspec>=0.12.1
